gemini_mcp/__init__.py
gemini_mcp/__main__.py
gemini_mcp/gemini_api.py
gemini_mcp/mcp_server.py
gemini_mcp-0.2.6.dist-info/METADATA
gemini_mcp-0.2.6.dist-info/WHEEL
gemini_mcp-0.2.6.dist-info/entry_points.txt
gemini_mcp-0.2.6.dist-info/licenses/LICENSE
gemini_mcp-0.2.6.dist-info/RECORD
