Metadata-Version: 2.4
Name: gemini-mcp
Version: 0.2.6
Summary: MCP server for Gemini AI image processing - 基于 Gemini 2.5 Flash 的图片处理 MCP 服务
Project-URL: Homepage, https://github.com/yourusername/gemini-mcp
Project-URL: Documentation, https://github.com/yourusername/gemini-mcp#readme
Project-URL: Repository, https://github.com/yourusername/gemini-mcp
Project-URL: Issues, https://github.com/yourusername/gemini-mcp/issues
Author-email: Your Name <your.email@example.com>
License: MIT
License-File: LICENSE
Keywords: ai,claude,gemini,image-processing,llm,mcp
Classifier: Development Status :: 4 - Beta
Classifier: Intended Audience :: Developers
Classifier: License :: OSI Approved :: MIT License
Classifier: Programming Language :: Python :: 3
Classifier: Programming Language :: Python :: 3.8
Classifier: Programming Language :: Python :: 3.9
Classifier: Programming Language :: Python :: 3.10
Classifier: Programming Language :: Python :: 3.11
Classifier: Programming Language :: Python :: 3.12
Classifier: Topic :: Scientific/Engineering :: Artificial Intelligence
Classifier: Topic :: Software Development :: Libraries :: Python Modules
Requires-Python: >=3.8
Requires-Dist: fastmcp>=0.1.0
Requires-Dist: httpx[socks]>=0.24.0
Requires-Dist: openai>=1.0.0
Requires-Dist: pillow>=10.0.0
Requires-Dist: python-dotenv>=1.0.0
Requires-Dist: socksio>=1.0.0
Provides-Extra: dev
Requires-Dist: black>=23.0.0; extra == 'dev'
Requires-Dist: pytest-asyncio>=0.21.0; extra == 'dev'
Requires-Dist: pytest>=7.0.0; extra == 'dev'
Requires-Dist: ruff>=0.1.0; extra == 'dev'
